{
  "sorted_middleware": [],
  "middleware": {
    "/": {
      "files": [
        "server/edge/chunks/ssr/_ed631f._.js",
        "server/edge/chunks/ssr/[root of the server]__98ef82._.js",
        "server/edge/chunks/ssr/edge-wrapper_5d9e44.js"
      ],
      "name": "middleware",
      "page": "/",
      "matchers": [
        {
          "regexp": "/:nextData(_next/data/[^/]{1,})?/((?!api|_next/static|_next/image|favicon.ico|logo.png).*)(.json)?",
          "originalSource": "/((?!api|_next/static|_next/image|favicon.ico|logo.png).*)"
        }
      ],
      "wasm": [],
      "assets": [
        {
          "name": "server/edge/chunks/ssr/_ed631f._.js.map",
          "filePath": "server/edge/chunks/ssr/_ed631f._.js.map"
        },
        {
          "name": "server/edge/chunks/ssr/_ed631f._.js",
          "filePath": "server/edge/chunks/ssr/_ed631f._.js"
        },
        {
          "name": "server/edge/chunks/ssr/[root of the server]__98ef82._.js.map",
          "filePath": "server/edge/chunks/ssr/[root of the server]__98ef82._.js.map"
        },
        {
          "name": "server/edge/chunks/ssr/[root of the server]__98ef82._.js",
          "filePath": "server/edge/chunks/ssr/[root of the server]__98ef82._.js"
        },
        {
          "name": "server/edge/chunks/ssr/edge-wrapper_5d9e44.js.map",
          "filePath": "server/edge/chunks/ssr/edge-wrapper_5d9e44.js.map"
        },
        {
          "name": "server/edge/chunks/ssr/edge-wrapper_5d9e44.js",
          "filePath": "server/edge/chunks/ssr/edge-wrapper_5d9e44.js"
        }
      ],
      "env": {
        "__NEXT_BUILD_ID": "development",
        "NEXT_SERVER_ACTIONS_ENCRYPTION_KEY": "pBvFFalkY/UYWn3STL0ImaDrVV4kyjnTHhaO9lmigys=",
        "__NEXT_PREVIEW_MODE_ID": "2ec767b102ad198d314ced16f9da0e48",
        "__NEXT_PREVIEW_MODE_ENCRYPTION_KEY": "50fcb03f3d5209046993dc934fe80805c180f1c21a34f03b4f533d2635b44718",
        "__NEXT_PREVIEW_MODE_SIGNING_KEY": "19d5add8d1b33a01847fcec441d80600d88cf5c81a5469cb3b48aa28a5573dfd"
      }
    }
  },
  "instrumentation": null,
  "functions": {}
}